HISTORY.md
LICENSE
MANIFEST.in
README.md
flask_endpoint.py
setup.py
flask_endpoint.egg-info/PKG-INFO
flask_endpoint.egg-info/SOURCES.txt
flask_endpoint.egg-info/dependency_links.txt
flask_endpoint.egg-info/not-zip-safe
flask_endpoint.egg-info/requires.txt
flask_endpoint.egg-info/top_level.txt