Metadata-Version: 1.1
Name: flask-endpoint
Version: 0.1
Summary: Endpoint based routing for Flask. Simple.
Home-page: http://github.com/rhyselsmore/flask-endpoint
Author: Rhys Elsmore
Author-email: me@rhys.io
License: Copyright (c) 2015, Rhys Elsmore <me@rhys.io>
